README.txt
pymobile-create-project
setup.py
./__init__.py
./serve.py
./settings.py
./shared.py
./wsfunc.py
./controllers/__init__.py
./controllers/alarmlist.py
./controllers/artist_example.py
./controllers/debug.py
./controllers/errorpages.py
./controllers/index_page.py
./controllers/livecounter_example.py
./controllers/login_example.py
./controllers/session_example.py
./controllers/websocketfunction.py
./controllers/wol_example.py
./controllers/zz_static_files.py
./models/__init__.py
./models/alarmlist.py
./models/alarmlist_example.py
./models/artist_db_example.py
./models/devicelist.py
./static/favicon.ico
./static/jqm142/css/jquery.mobile-1.4.2.min.css
./static/jqm142/css/jquery.mobile.external-png-1.4.2.min.css
./static/jqm142/css/jquery.mobile.icons-1.4.2.min.css
./static/jqm142/css/jquery.mobile.inline-png-1.4.2.min.css
./static/jqm142/css/jquery.mobile.inline-svg-1.4.2.min.css
./static/jqm142/css/jquery.mobile.structure-1.4.2.min.css
./static/jqm142/css/jquery.mobile.theme-1.4.2.min.css
./static/jqm142/css/images/ajax-loader.gif
./static/jqm142/css/images/icons-png/action-black.png
./static/jqm142/css/images/icons-png/action-white.png
./static/jqm142/css/images/icons-png/alert-black.png
./static/jqm142/css/images/icons-png/alert-white.png
./static/jqm142/css/images/icons-png/arrow-d-black.png
./static/jqm142/css/images/icons-png/arrow-d-l-black.png
./static/jqm142/css/images/icons-png/arrow-d-l-white.png
./static/jqm142/css/images/icons-png/arrow-d-r-black.png
./static/jqm142/css/images/icons-png/arrow-d-r-white.png
./static/jqm142/css/images/icons-png/arrow-d-white.png
./static/jqm142/css/images/icons-png/arrow-l-black.png
./static/jqm142/css/images/icons-png/arrow-l-white.png
./static/jqm142/css/images/icons-png/arrow-r-black.png
./static/jqm142/css/images/icons-png/arrow-r-white.png
./static/jqm142/css/images/icons-png/arrow-u-black.png
./static/jqm142/css/images/icons-png/arrow-u-l-black.png
./static/jqm142/css/images/icons-png/arrow-u-l-white.png
pymobile.egg-info/PKG-INFO
pymobile.egg-info/SOURCES.txt
pymobile.egg-info/dependency_links.txt
pymobile.egg-info/top_level.txt