Metadata-Version: 1.1
Name: pymobile
Version: 0.1.0
Summary: Webframework using bottle, asyncio, websockets, jquery and jquery-mobile
Home-page: https://bitbucket.org/fholmer/pymobile
Author: Frode Holmer
Author-email: fholmer@gmail.com
License: GPLv3
Keywords: pymobile jquery mobile websocket asyncio bottle web framework
Platform: UNKNOWN
Classifier: Development Status :: 4 - Beta
Classifier: Environment :: Web Environment
Classifier: Intended Audience :: Developers
Classifier: License :: OSI Approved :: GNU General Public License v3 (GPLv3)
Classifier: Operating System :: POSIX :: Linux
Classifier: Programming Language :: Python :: 3
Classifier: Programming Language :: Python :: 3.4
Classifier: Topic :: Internet :: WWW/HTTP
Classifier: Topic :: Internet :: WWW/HTTP :: HTTP Servers
Requires: bottle
Requires: asyncio
Requires: websockets
Provides: pymobile (0.1.0)
